MANIFEST.in
README.rst
TITLE.txt
lh-agpl3-LICENSE.txt
setup.py
unisos/__init__.py
unisos.x822Msg.egg-info/PKG-INFO
unisos.x822Msg.egg-info/SOURCES.txt
unisos.x822Msg.egg-info/dependency_links.txt
unisos.x822Msg.egg-info/namespace_packages.txt
unisos.x822Msg.egg-info/not-zip-safe
unisos.x822Msg.egg-info/requires.txt
unisos.x822Msg.egg-info/top_level.txt
unisos/x822Msg/__init__.py
unisos/x822Msg/msgIn.py
unisos/x822Msg/msgLib.py
unisos/x822Msg/msgOut.py